tsgm
