Metadata-Version: 2.4
Name: tsgm
Version: 0.1.0
Summary: Time Series Generative Modelling Framework
Home-page: https://github.com/AlexanderVNikitin/tsgm
Download-URL: 
Author: Alexander Nikitin
Author-email: 
Maintainer: Alexander Nikitin
Maintainer-email: 
License: Apache-2.0
Keywords: machine learning,deep learning,signal processing,temporal signal,time series,generative modeling,neural networks,GAN
License-File: LICENSE
Requires-Dist: scipy>=1.9.0
Requires-Dist: numpy>=2.0
Requires-Dist: networkx<3.3,>=3.1
Requires-Dist: seaborn>=0.13.2
Requires-Dist: scikit-learn>=1.6.1
Requires-Dist: prettytable==3.16.0
Requires-Dist: antropy==0.1.6
Requires-Dist: yfinance==0.2.61
Requires-Dist: tqdm>=4.67.1
Requires-Dist: dtaidistance==2.3.13
Requires-Dist: keras>=3.10.0
Requires-Dist: statsmodels==0.14.5
Provides-Extra: tensorflow
Requires-Dist: tensorflow>=2.19.0; extra == "tensorflow"
Requires-Dist: tensorflow-probability>=0.25.0; extra == "tensorflow"
Requires-Dist: tf-keras>=2.19.0; extra == "tensorflow"
Provides-Extra: torch
Requires-Dist: torch>=2.6.0; extra == "torch"
Requires-Dist: torchvision>=0.21.0; extra == "torch"
Provides-Extra: jax
Requires-Dist: jax>=0.4.30; extra == "jax"
Requires-Dist: jaxlib>=0.4.30; extra == "jax"
Provides-Extra: all
Requires-Dist: tensorflow>=2.19.0; extra == "all"
Requires-Dist: tensorflow-probability>=0.25.0; extra == "all"
Requires-Dist: tf-keras>=2.19.1; extra == "all"
Requires-Dist: torch>=2.6.0; extra == "all"
Requires-Dist: torchvision>=0.21.0; extra == "all"
Requires-Dist: jax>=0.4.30; extra == "all"
Requires-Dist: jaxlib>=0.4.30; extra == "all"
Dynamic: author
Dynamic: description
Dynamic: description-content-type
Dynamic: home-page
Dynamic: keywords
Dynamic: license
Dynamic: license-file
Dynamic: maintainer
Dynamic: provides-extra
Dynamic: requires-dist
Dynamic: summary
